pyrepositories/__init__.py
pyrepositories/datasource.py
pyrepositories/datatable.py
pyrepositories/json_repository.py
pyrepositories/lib.py
pyrepositories/pg_repository.py
pyrepositories-2.1.1.dist-info/METADATA
pyrepositories-2.1.1.dist-info/WHEEL
pyrepositories-2.1.1.dist-info/top_level.txt
pyrepositories-2.1.1.dist-info/RECORD
